{
  "id": "20f9f468-04e6-4d8a-9e5c-c6dcb2f016a6",
  "prevId": "730edefd-204d-42a1-a757-aed86b1ec282",
  "version": "7",
  "dialect": "postgresql",
  "tables": {
    "public.transcript_chunks": {
      "name": "transcript_chunks",
      "schema": "",
      "columns": {
        "id": {
          "name": "id",
          "type": "text",
          "primaryKey": true,
          "notNull": true
        },
        "transcript_id": {
          "name": "transcript_id",
          "type": "integer",
          "primaryKey": false,
          "notNull": true
        },
        "page_number": {
          "name": "page_number",
          "type": "integer",
          "primaryKey": false,
          "notNull": true
        },
        "from_line": {
          "name": "from_line",
          "type": "integer",
          "primaryKey": false,
          "notNull": true
        },
        "to_line": {
          "name": "to_line",
          "type": "integer",
          "primaryKey": false,
          "notNull": true
        },
        "embedding": {
          "name": "embedding",
          "type": "vector(1536)",
          "primaryKey": false,
          "notNull": false
        }
      },
      "indexes": {
        "transcript_chunks_embedding_index": {
          "name": "transcript_chunks_embedding_index",
          "columns": [
            {
              "expression": "embedding",
              "isExpression": false,
              "asc": true,
              "nulls": "last",
              "opclass": "vector_cosine_ops"
            }
          ],
          "isUnique": false,
          "concurrently": false,
          "method": "hnsw",
          "with": {}
        }
      },
      "foreignKeys": {},
      "compositePrimaryKeys": {},
      "uniqueConstraints": {}
    },
    "public.transcripts": {
      "name": "transcripts",
      "schema": "",
      "columns": {
        "id": {
          "name": "id",
          "type": "text",
          "primaryKey": true,
          "notNull": true
        },
        "name": {
          "name": "name",
          "type": "text",
          "primaryKey": false,
          "notNull": true
        },
        "total_pages": {
          "name": "total_pages",
          "type": "integer",
          "primaryKey": false,
          "notNull": true
        }
      },
      "indexes": {},
      "foreignKeys": {},
      "compositePrimaryKeys": {},
      "uniqueConstraints": {}
    }
  },
  "enums": {},
  "schemas": {},
  "sequences": {},
  "_meta": {
    "columns": {},
    "schemas": {},
    "tables": {}
  }
}